orchstr8/__init__.py
orchstr8/cli.py
orchstr8/conductor.py
orchstr8/fixture.py
orchstr8/services.py
orchstr8/testcase.py
orchstr8-0.0.4.dist-info/METADATA
orchstr8-0.0.4.dist-info/RECORD
orchstr8-0.0.4.dist-info/WHEEL
orchstr8-0.0.4.dist-info/entry_points.txt
orchstr8-0.0.4.dist-info/top_level.txt
