Metadata-Version: 2.1
Name: orchstr8
Version: 0.0.4
Summary: Services orchestration and testing library for torba and electrumx based projects.
Home-page: https://github.com/lbryio/orchstr8
Author: LBRY Inc.
Author-email: hello@lbry.io
License: MIT
Keywords: bitcoin,torba,electrumx,lbry
Platform: UNKNOWN
Classifier: Framework :: AsyncIO
Classifier: Framework :: Twisted
Classifier: Intended Audience :: Developers
Classifier: Intended Audience :: System Administrators
Classifier: License :: OSI Approved :: MIT License
Classifier: Programming Language :: Python :: 3
Classifier: Operating System :: OS Independent
Classifier: Topic :: Internet
Classifier: Topic :: Communications :: File Sharing
Classifier: Topic :: Software Development :: Testing
Classifier: Topic :: Software Development :: Libraries :: Python Modules
Classifier: Topic :: System :: Benchmark
Classifier: Topic :: System :: Distributed Computing
Classifier: Topic :: Utilities
Requires-Python: >=3.6
Requires-Dist: requests
Requires-Dist: twisted
